[
 
{
"name": "Saugat Adhikari",
"address": "Pokhara",
"skills": ["Web Developer", "Graphics Designer", "MERN Stack Dev"],
"githubUsername": "saugat-adhikari",
"instagramUsername": "saugaat_adhikari",
"facebookUsername": "saugat0"
},{
 "name":"Arjun Adhikari",
 "address":"Butwal",
 "skills":["Java","NodeJS","Kotlin"],
 "githubUsername":"arjunadhikary",
 "instagramUsername":"arjun_adhikary",
 "facebookUsername":"reasonworld123"
},
 {
 "name": "Sandesh Sharma",
 "address":"Pokhara",
 "skills":["Flutter","NodeJS","Kotlin"],
 "githubUsername":"Sandesh-Sharma",
 "instagramUsername":"thesanshar",
 "facebookUsername":"thesandeshsharma"
},
 {
 "name": "Bikram Parajuli",
 "address":"Pokhara",
 "skills":["Flutter","NodeJS","Python"],
 "githubUsername":"ParajuliBkrm",
 "instagramUsername":"Parajuli.Bkrm",
 "facebookUsername":"ParajuliBkrm"
},
 {
 "name": "Shankar Kharel",
 "address":"Butwal",
 "skills":["Flutter","Java","Python"],
 "githubUsername":"shankarkharel",
 "instagramUsername":"shankarkharel35",
 "facebookUsername":"Shankar Kharel"
},
 {
 "name": "Agni Pradhan",
 "address":"Pokhara",
 "skills":["Flutter","Java","Python","Linux"],
 "githubUsername":"agnipradhan",
 "instagramUsername":"codekavya",
 "facebookUsername":"agni.pradhan.3"
},
 
]
